colander_jsonschema
