Metadata-Version: 1.1
Name: colander-jsonschema
Version: 0.2
Summary: JSON-Schema converter for colander
Home-page: https://github.com/gjo/colander_jsonschema
Author: OCHIAI, Gouji
Author-email: gjo.ext@gmail.com
License: BSD
Platform: UNKNOWN
Classifier: Environment :: Console
Classifier: Framework :: Pylons
Classifier: Intended Audience :: Developers
Classifier: License :: OSI Approved :: BSD License
Classifier: Programming Language :: Python
Classifier: Programming Language :: Python :: 2.7
Classifier: Programming Language :: Python :: 3.3
Classifier: Programming Language :: Python :: 3.4
Classifier: Topic :: Internet :: WWW/HTTP :: Site Management
Classifier: Topic :: Software Development :: Code Generators
Classifier: Topic :: Text Processing
